mrhlpr/__init__.py
mrhlpr/frontend.py
mrhlpr/git.py
mrhlpr/gitlab.py
mrhlpr/mr.py
mrhlpr/mrdb.py
mrhlpr/pipeline.py
mrhlpr/runner.py
mrtest/__init__.py
mrtest/add_packages.py
mrtest/apk_installed.py
mrtest/frontend.py
mrtest/origin.py
mrtest/select_package.py
mrtest/zap_packages.py
mrhlpr-1.0.0.dist-info/LICENSE
mrhlpr-1.0.0.dist-info/METADATA
mrhlpr-1.0.0.dist-info/WHEEL
mrhlpr-1.0.0.dist-info/entry_points.txt
mrhlpr-1.0.0.dist-info/top_level.txt
mrhlpr-1.0.0.dist-info/RECORD
