Metadata-Version: 2.1
Name: mrhlpr
Version: 1.0.0
Summary: postmarketOS tools for interacting with gitlab MRs
Home-page: https://www.postmarketos.org
Author: postmarketOS Developers
Author-email: info@postmarketos.org
License: GPLv3
Keywords: postmarketos gitlab
Platform: UNKNOWN
Classifier: Development Status :: 5 - Production/Stable
Classifier: Intended Audience :: Developers
Classifier: License :: OSI Approved :: GNU General Public License v3 (GPLv3)
Classifier: Programming Language :: Python :: 3
Classifier: Programming Language :: Python :: 3.6
Classifier: Programming Language :: Python :: 3.7
Classifier: Programming Language :: Python :: 3.8
Requires-Python: >=3.6
License-File: LICENSE
Provides-Extra: completion
Requires-Dist: argcomplete ; extra == 'completion'
